cwsapiwrapper/__init__.py
cwsapiwrapper/api.py
cwsapiwrapper/helpers.py
cwsapiwrapper-1.0.dist-info/LICENSE
cwsapiwrapper-1.0.dist-info/METADATA
cwsapiwrapper-1.0.dist-info/WHEEL
cwsapiwrapper-1.0.dist-info/top_level.txt
cwsapiwrapper-1.0.dist-info/RECORD
