Metadata-Version: 2.1
Name: cwsapiwrapper
Version: 1.0
Summary: A wrapper for the ConWorkShop API
Home-page: https://github.com/yourusername/my_package
Author: Nemirphen
Author-email: hikaru_dano@vk.com
Classifier: Programming Language :: Python :: 3
Classifier: License :: OSI Approved :: MIT License
Classifier: Operating System :: OS Independent
Requires-Python: >=3.6
License-File: LICENSE
